geneal/__init__.py
geneal/applications/__init__.py
geneal/applications/fitness_functions/__init__.py
geneal/applications/fitness_functions/binary.py
geneal/applications/fitness_functions/continuous.py
geneal/applications/template.py
geneal/applications/tsp/__init__.py
geneal/applications/tsp/examples/__init__.py
geneal/applications/tsp/examples/cities.py
geneal/applications/tsp/examples/us_cities/__init__.py
geneal/applications/tsp/examples/us_cities/_us_cities.py
geneal/applications/tsp/examples/us_cities/graph.py
geneal/applications/tsp/examples/world_capitals/__init__.py
geneal/applications/tsp/examples/world_capitals/_world_capitals.py
geneal/applications/tsp/examples/world_capitals/graph.py
geneal/applications/tsp/helpers/__init__.py
geneal/applications/tsp/helpers/_create_graph.py
geneal/applications/tsp/helpers/_plot_cities.py
geneal/applications/tsp/mutation_strategies.py
geneal/applications/tsp/travelling_salesman_problem.py
geneal/genetic_algorithms/__init__.py
geneal/genetic_algorithms/_binary.py
geneal/genetic_algorithms/_continuous.py
geneal/genetic_algorithms/genetic_algorithm_base.py
geneal/utils/exceptions.py
geneal/utils/exceptions_messages.py
geneal/utils/helpers.py
geneal/utils/logger.py
geneal/version.py
geneal-0.8.3.dist-info/METADATA
geneal-0.8.3.dist-info/WHEEL
geneal-0.8.3.dist-info/RECORD
