Metadata-Version: 2.3
Name: geneal
Version: 0.8.3
Summary: Python Genetic Algorithm library
License: MIT
Keywords: genetic algorithms,ga,optimization,genetic programming
Author: Diogo Matos Chaves
Author-email: diogo_chaves@hotmail.com
Requires-Python: >=3.9,<3.13
Classifier: License :: OSI Approved :: MIT License
Classifier: Programming Language :: Python :: 3
Classifier: Programming Language :: Python :: 3.9
Classifier: Programming Language :: Python :: 3.10
Classifier: Programming Language :: Python :: 3.11
Classifier: Programming Language :: Python :: 3.12
Requires-Dist: descartes (==1.1.0)
Requires-Dist: ipykernel (==6.16.0)
Requires-Dist: matplotlib (>=3.8,<4.0)
Requires-Dist: nbformat (==5.6.1)
Requires-Dist: networkx (==2.6.3)
Requires-Dist: numba (>=0.59,<0.60)
Requires-Dist: numpy (>=1.26,<2.0)
Requires-Dist: pandas (>=2.1,<3.0)
Requires-Dist: plotly (>=5.10.0,<6.0.0)
Requires-Dist: scipy (>=1.7.3,<2.0.0)
Project-URL: Repository, https://github.com/diogomatoschaves/geneal
